DucksTools/DucksTools.py
DucksTools/__init__.py
DucksTools/datasets.py
DucksTools/display_mixin.py
DucksTools/drop_features_mixin.py
DucksTools/drop_records_mixin.py
DucksTools/encode_mixin.py
DucksTools/feature_target_split_mixin.py
DucksTools/feature_type_mixin.py
DucksTools/impute_features_mixin.py
DucksTools/missing_data_summary_mixin.py
DucksTools/oversample_mixin.py
DucksTools/pre_process_mixin.py
DucksTools/sample_data_mixin.py
DucksTools/scale_mixin.py
DucksTools/split_dataframe_mixin.py
DucksTools/to_numeric_mixin.py
DucksTools/transform_mixin.py
DucksTools/unique_value_summary_mixin.py
DucksTools/data/__init__.py
dukstools-0.1.16.dist-info/licenses/LICENSE
dukstools-0.1.16.dist-info/METADATA
dukstools-0.1.16.dist-info/WHEEL
dukstools-0.1.16.dist-info/top_level.txt
dukstools-0.1.16.dist-info/RECORD
